georss_nrcan_earthquakes_client/__init__.py
georss_nrcan_earthquakes_client/__version__.py
georss_nrcan_earthquakes_client-0.4.dist-info/LICENSE
georss_nrcan_earthquakes_client-0.4.dist-info/METADATA
georss_nrcan_earthquakes_client-0.4.dist-info/WHEEL
georss_nrcan_earthquakes_client-0.4.dist-info/top_level.txt
georss_nrcan_earthquakes_client-0.4.dist-info/RECORD
