Metadata-Version: 2.1
Name: georss-nrcan-earthquakes-client
Version: 0.4
Summary: A GeoRSS client library for the Natural Resources Canada Earthquakes feed.
Home-page: https://github.com/exxamalte/python-georss-nrcan-earthquakes-client
Author: Malte Franken
Author-email: coding@subspace.de
License: Apache-2.0
Platform: UNKNOWN
Classifier: Programming Language :: Python :: 3.7
Classifier: Programming Language :: Python :: 3.8
Classifier: Programming Language :: Python :: 3.9
Classifier: Programming Language :: Python :: 3.10
Classifier: License :: OSI Approved :: Apache Software License
Classifier: Operating System :: OS Independent
Requires-Dist: georss-client (>=0.15)
